{"singlePage": [], "startSite": "", "filingNum": "", "onePageListNum": 15, "commentLabelColor": "#006b75", "yearColorList": ["#bc4c00", "#0969da", "#1f883d", "#A333D0"], "i18n": "CN", "themeMode": "manual", "dayTheme": "light", "nightTheme": "dark", "urlMode": "pinyin", "script": "", "style": "", "head": "", "indexScript": "", "indexStyle": "", "bottomText": "", "showPostSource": 1, "iconList": {}, "UTC": 8, "rssSplit": "sentence", "exlink": {}, "needComment": 1, "allHead": "", "title": "Blog Title", "subTitle": "Blog description", "avatarUrl": "https://github.githubassets.com/favicons/favicon.svg", "GMEEK_VERSION": "last", "postListJson": {"P1": {"htmlDir": "docs/post/zhong-guo-yi-dong-yun-pan.html", "labels": ["wontfix"], "postTitle": "\u4e2d\u56fd\u79fb\u52a8\u4e91\u76d8", "postUrl": "post/zhong-guo-yi-dong-yun-pan.html", "postSourceUrl": "https://github.com/stwy0716/Cloud-disk-homepage/issues/1", "commentNum": 0, "wordCount": 6, "description": "\u5976\u5976\u6ca1\u4e8b\u94fe\u63a5\u3002", "top": 0, "createdAt": 1737195340, "style": "", "script": "", "head": "", "ogImage": "https://github.githubassets.com/favicons/favicon.svg", "createdDate": "2025-01-18", "dateLabelColor": "#0969da"}}, "singeListJson": {}, "labelColorDict": {"bug": "#d73a4a", "documentation": "#0075ca", "duplicate": "#cfd3d7", "enhancement": "#a2eeef", "good first issue": "#7057ff", "help wanted": "#008672", "invalid": "#e4e669", "question": "#d876e3", "wontfix": "#ffffff"}, "displayTitle": "Blog Title", "faviconUrl": "https://github.githubassets.com/favicons/favicon.svg", "ogImage": "https://github.githubassets.com/favicons/favicon.svg", "primerCSS": "<link href='https://mirrors.sustech.edu.cn/cdnjs/ajax/libs/Primer/21.0.7/primer.css' rel='stylesheet' />", "homeUrl": "https://stwy0716.github.io/Cloud-disk-homepage", "prevUrl": "disabled", "nextUrl": "disabled"}